model/__init__.py
model/sample.py
model/stDiff_model.py
model/stDiff_scheduler.py
model/stDiff_train.py
process/__init__.py
process/data.py
process/data_process.py
process/result_analysis.py
stDiff_sc-1.1.4.dist-info/LICENSE
stDiff_sc-1.1.4.dist-info/METADATA
stDiff_sc-1.1.4.dist-info/WHEEL
stDiff_sc-1.1.4.dist-info/top_level.txt
stDiff_sc-1.1.4.dist-info/RECORD
