Metadata-Version: 2.1
Name: stDiff-sc
Version: 1.1.4
Summary: a diffusion model to impute ST data by learn scRNA-seq data
Home-page: https://github.com/fdu-wangfeilab/stDiff
Author: Kongming Li
Author-email: 23210240023@m.fudan.edu.cn
License: UNKNOWN
Platform: UNKNOWN
Classifier: Programming Language :: Python :: 3
Classifier: License :: OSI Approved :: MIT License
License-File: LICENSE
Requires-Dist: anndata (==0.7.8)
Requires-Dist: einops (==0.4.1)
Requires-Dist: matplotlib
Requires-Dist: numpy (==1.19.5)
Requires-Dist: pandas (==1.1.5)
Requires-Dist: ray (==2.4.0)
Requires-Dist: scanpy (==1.7.2)
Requires-Dist: scikit-learn (==0.24.2)
Requires-Dist: scipy (==1.5.4)
Requires-Dist: seaborn (==0.11.1)
Requires-Dist: timm (==0.6.12)
Requires-Dist: torch (==1.9.0)
Requires-Dist: tqdm (==4.61.1)
